jsonc/__init__.py
jsonc/_add_comments.py
jsonc/_types.py
jsonc/_util.py
jsonc/_version.py
json_with_comments-1.2.9.dist-info/METADATA
json_with_comments-1.2.9.dist-info/WHEEL
json_with_comments-1.2.9.dist-info/licenses/LICENSE
json_with_comments-1.2.9.dist-info/RECORD
